[
  {
    "WeatherEnd" : "Clear",
    "Layout" : "",
    "LapTimeMs" : 105890,
    "WeatherStart" : "Clear",
    "Track" : "ks_laguna_seca",
    "WeatherCategory" : "Clear",
    "TimestampMs" : 1774819898183,
    "SessionId" : "a0e48b87-bce6-4f92-af5e-279ba98811e9",
    "Car" : "mclaren_mp412c_gt3"
  },
  {
    "Car" : "mclaren_mp412c_gt3",
    "WeatherCategory" : "Clear",
    "Track" : "ks_laguna_seca",
    "SessionId" : "a0e48b87-bce6-4f92-af5e-279ba98811e9",
    "TimestampMs" : 1774820127972,
    "WeatherEnd" : "Clear",
    "LapTimeMs" : 122534,
    "Layout" : "",
    "WeatherStart" : "Clear"
  },
  {
    "LapTimeMs" : 109723,
    "Layout" : "",
    "WeatherStart" : "Clear",
    "WeatherEnd" : "Clear",
    "Track" : "ks_laguna_seca",
    "WeatherCategory" : "Clear",
    "SessionId" : "a0e48b87-bce6-4f92-af5e-279ba98811e9",
    "TimestampMs" : 1774820818368,
    "Car" : "ferrari_458_gt2"
  },
  {
    "Car" : "ferrari_458_gt2",
    "WeatherEnd" : "Clear",
    "WeatherStart" : "Clear",
    "LapTimeMs" : 95239,
    "Layout" : "",
    "TimestampMs" : 1774820913607,
    "SessionId" : "a0e48b87-bce6-4f92-af5e-279ba98811e9",
    "Track" : "ks_laguna_seca",
    "WeatherCategory" : "Clear"
  },
  {
    "WeatherEnd" : "Clear",
    "Layout" : "",
    "LapTimeMs" : 99496,
    "WeatherStart" : "Clear",
    "WeatherCategory" : "Clear",
    "Track" : "ks_laguna_seca",
    "SessionId" : "a0e48b87-bce6-4f92-af5e-279ba98811e9",
    "TimestampMs" : 1774821013103,
    "Car" : "ferrari_458_gt2"
  },
  {
    "Car" : "ferrari_458_gt2",
    "Track" : "ks_laguna_seca",
    "WeatherCategory" : "Clear",
    "TimestampMs" : 1774821660127,
    "SessionId" : "a0e48b87-bce6-4f92-af5e-279ba98811e9",
    "WeatherEnd" : "Clear",
    "LapTimeMs" : 95288,
    "Layout" : "",
    "WeatherStart" : "Clear"
  },
  {
    "Car" : "ferrari_458_gt2",
    "WeatherEnd" : "Clear",
    "LapTimeMs" : 92221,
    "Layout" : "",
    "WeatherStart" : "Clear",
    "Track" : "ks_laguna_seca",
    "WeatherCategory" : "Clear",
    "SessionId" : "a0e48b87-bce6-4f92-af5e-279ba98811e9",
    "TimestampMs" : 1774821752335
  },
  {
    "Layout" : "",
    "LapTimeMs" : 98496,
    "WeatherStart" : "Clear",
    "WeatherEnd" : "Clear",
    "WeatherCategory" : "Clear",
    "Track" : "ks_laguna_seca",
    "TimestampMs" : 1774822479291,
    "SessionId" : "a0e48b87-bce6-4f92-af5e-279ba98811e9",
    "Car" : "ferrari_458_gt2"
  },
  {
    "TimestampMs" : 1774822571892,
    "SessionId" : "a0e48b87-bce6-4f92-af5e-279ba98811e9",
    "WeatherCategory" : "Clear",
    "Track" : "ks_laguna_seca",
    "WeatherEnd" : "Clear",
    "WeatherStart" : "Clear",
    "LapTimeMs" : 92601,
    "Layout" : "",
    "Car" : "ferrari_458_gt2"
  },
  {
    "Track" : "ks_laguna_seca",
    "WeatherCategory" : "Clear",
    "TimestampMs" : 1774823042900,
    "SessionId" : "a0e48b87-bce6-4f92-af5e-279ba98811e9",
    "Layout" : "",
    "LapTimeMs" : 93045,
    "WeatherStart" : "Clear",
    "WeatherEnd" : "Clear",
    "Car" : "ferrari_458_gt2"
  },
  {
    "Car" : "ferrari_458_gt2",
    "SessionId" : "a0e48b87-bce6-4f92-af5e-279ba98811e9",
    "TimestampMs" : 1774823405777,
    "WeatherCategory" : "Clear",
    "Track" : "ks_laguna_seca",
    "WeatherEnd" : "Clear",
    "WeatherStart" : "Clear",
    "LapTimeMs" : 92672,
    "Layout" : ""
  },
  {
    "Car" : "ferrari_458_gt2",
    "WeatherStart" : "Clear",
    "Layout" : "",
    "LapTimeMs" : 100695,
    "WeatherEnd" : "Clear",
    "SessionId" : "a0e48b87-bce6-4f92-af5e-279ba98811e9",
    "TimestampMs" : 1774823506471,
    "WeatherCategory" : "Clear",
    "Track" : "ks_laguna_seca"
  },
  {
    "Track" : "ks_laguna_seca",
    "WeatherCategory" : "Clear",
    "SessionId" : "a0e48b87-bce6-4f92-af5e-279ba98811e9",
    "TimestampMs" : 1774823603298,
    "WeatherEnd" : "Clear",
    "Layout" : "",
    "LapTimeMs" : 96830,
    "WeatherStart" : "Clear",
    "Car" : "ferrari_458_gt2"
  },
  {
    "WeatherCategory" : "Clear",
    "Track" : "ks_laguna_seca",
    "SessionId" : "a0e48b87-bce6-4f92-af5e-279ba98811e9",
    "TimestampMs" : 1774823819535,
    "LapTimeMs" : 108648,
    "Layout" : "",
    "WeatherStart" : "Clear",
    "WeatherEnd" : "Clear",
    "Car" : "ferrari_458_gt2"
  },
  {
    "Car" : "ferrari_458_gt2",
    "SessionId" : "a0e48b87-bce6-4f92-af5e-279ba98811e9",
    "TimestampMs" : 1774824087612,
    "WeatherCategory" : "Clear",
    "Track" : "ks_laguna_seca",
    "WeatherStart" : "Clear",
    "Layout" : "",
    "LapTimeMs" : 97372,
    "WeatherEnd" : "Clear"
  },
  {
    "SessionId" : "a0e48b87-bce6-4f92-af5e-279ba98811e9",
    "TimestampMs" : 1774824181662,
    "WeatherCategory" : "Clear",
    "Track" : "ks_laguna_seca",
    "WeatherStart" : "Clear",
    "LapTimeMs" : 94051,
    "Layout" : "",
    "WeatherEnd" : "Clear",
    "Car" : "ferrari_458_gt2"
  },
  {
    "SessionId" : "a0e48b87-bce6-4f92-af5e-279ba98811e9",
    "TimestampMs" : 1774824275893,
    "WeatherCategory" : "Clear",
    "Track" : "ks_laguna_seca",
    "WeatherEnd" : "Clear",
    "WeatherStart" : "Clear",
    "LapTimeMs" : 94231,
    "Layout" : "",
    "Car" : "ferrari_458_gt2"
  },
  {
    "Car" : "ferrari_458_gt2",
    "WeatherEnd" : "Clear",
    "Layout" : "",
    "LapTimeMs" : 106798,
    "WeatherStart" : "Clear",
    "WeatherCategory" : "Clear",
    "Track" : "ks_laguna_seca",
    "TimestampMs" : 1774824535732,
    "SessionId" : "a0e48b87-bce6-4f92-af5e-279ba98811e9"
  },
  {
    "Car" : "ferrari_458_gt2",
    "LapTimeMs" : 93395,
    "Layout" : "",
    "WeatherStart" : "Clear",
    "WeatherEnd" : "Clear",
    "WeatherCategory" : "Clear",
    "Track" : "ks_laguna_seca",
    "SessionId" : "a0e48b87-bce6-4f92-af5e-279ba98811e9",
    "TimestampMs" : 1774824966358
  },
  {
    "SessionId" : "a0e48b87-bce6-4f92-af5e-279ba98811e9",
    "TimestampMs" : 1774825225084,
    "WeatherCategory" : "Clear",
    "Track" : "ks_laguna_seca",
    "WeatherEnd" : "Clear",
    "WeatherStart" : "Clear",
    "LapTimeMs" : 90234,
    "Layout" : "",
    "Car" : "ferrari_458_gt2"
  },
  {
    "Track" : "ks_laguna_seca",
    "WeatherCategory" : "Clear",
    "SessionId" : "a0e48b87-bce6-4f92-af5e-279ba98811e9",
    "TimestampMs" : 1774825322303,
    "Layout" : "",
    "LapTimeMs" : 97218,
    "WeatherStart" : "Clear",
    "WeatherEnd" : "Clear",
    "Car" : "ferrari_458_gt2"
  },
  {
    "WeatherEnd" : "Clear",
    "WeatherStart" : "Clear",
    "Layout" : "",
    "LapTimeMs" : 91256,
    "TimestampMs" : 1774825753994,
    "SessionId" : "a0e48b87-bce6-4f92-af5e-279ba98811e9",
    "Track" : "ks_laguna_seca",
    "WeatherCategory" : "Clear",
    "Car" : "ferrari_458_gt2"
  },
  {
    "WeatherStart" : "Clear",
    "Layout" : "",
    "LapTimeMs" : 88805,
    "WeatherEnd" : "Clear",
    "TimestampMs" : 1774825842794,
    "SessionId" : "a0e48b87-bce6-4f92-af5e-279ba98811e9",
    "WeatherCategory" : "Clear",
    "Track" : "ks_laguna_seca",
    "Car" : "ferrari_458_gt2"
  },
  {
    "WeatherCategory" : "Clear",
    "Track" : "ks_laguna_seca",
    "TimestampMs" : 1774825934903,
    "SessionId" : "a0e48b87-bce6-4f92-af5e-279ba98811e9",
    "WeatherEnd" : "Clear",
    "Layout" : "",
    "LapTimeMs" : 92109,
    "WeatherStart" : "Clear",
    "Car" : "ferrari_458_gt2"
  },
  {
    "WeatherCategory" : "Clear",
    "Track" : "ks_laguna_seca",
    "SessionId" : "a0e48b87-bce6-4f92-af5e-279ba98811e9",
    "TimestampMs" : 1774826024238,
    "LapTimeMs" : 89334,
    "Layout" : "",
    "WeatherStart" : "Clear",
    "WeatherEnd" : "Clear",
    "Car" : "ferrari_458_gt2"
  },
  {
    "Car" : "ferrari_458_gt2",
    "WeatherEnd" : "Clear",
    "Layout" : "",
    "LapTimeMs" : 89693,
    "WeatherStart" : "Clear",
    "WeatherCategory" : "Clear",
    "Track" : "ks_laguna_seca",
    "TimestampMs" : 1774826113930,
    "SessionId" : "a0e48b87-bce6-4f92-af5e-279ba98811e9"
  },
  {
    "Car" : "ferrari_458_gt2",
    "WeatherEnd" : "Clear",
    "Layout" : "",
    "LapTimeMs" : 92720,
    "WeatherStart" : "Clear",
    "Track" : "ks_laguna_seca",
    "WeatherCategory" : "Clear",
    "SessionId" : "a0e48b87-bce6-4f92-af5e-279ba98811e9",
    "TimestampMs" : 1774826206647
  },
  {
    "Car" : "ferrari_458_gt2",
    "WeatherCategory" : "Clear",
    "Track" : "ks_laguna_seca",
    "TimestampMs" : 1774826298393,
    "SessionId" : "a0e48b87-bce6-4f92-af5e-279ba98811e9",
    "WeatherEnd" : "Clear",
    "LapTimeMs" : 91748,
    "Layout" : "",
    "WeatherStart" : "Clear"
  },
  {
    "SessionId" : "a0e48b87-bce6-4f92-af5e-279ba98811e9",
    "TimestampMs" : 1774826774716,
    "Track" : "ks_laguna_seca",
    "WeatherCategory" : "Clear",
    "WeatherStart" : "Clear",
    "LapTimeMs" : 94024,
    "Layout" : "",
    "WeatherEnd" : "Clear",
    "Car" : "ferrari_458_gt2"
  },
  {
    "Car" : "bmw_z4_gt3",
    "WeatherEnd" : "Clear",
    "WeatherStart" : "Clear",
    "LapTimeMs" : 88821,
    "Layout" : "",
    "TimestampMs" : 1774827326329,
    "SessionId" : "a0e48b87-bce6-4f92-af5e-279ba98811e9",
    "Track" : "ks_laguna_seca",
    "WeatherCategory" : "Clear"
  },
  {
    "Car" : "bmw_z4_gt3",
    "WeatherEnd" : "Clear",
    "WeatherStart" : "Clear",
    "Layout" : "",
    "LapTimeMs" : 102802,
    "SessionId" : "a0e48b87-bce6-4f92-af5e-279ba98811e9",
    "TimestampMs" : 1774827526223,
    "Track" : "ks_laguna_seca",
    "WeatherCategory" : "Clear"
  },
  {
    "TimestampMs" : 1774827615259,
    "SessionId" : "a0e48b87-bce6-4f92-af5e-279ba98811e9",
    "Track" : "ks_laguna_seca",
    "WeatherCategory" : "Clear",
    "WeatherEnd" : "Clear",
    "WeatherStart" : "Clear",
    "Layout" : "",
    "LapTimeMs" : 89038,
    "Car" : "bmw_z4_gt3"
  },
  {
    "Car" : "bmw_z4_gt3",
    "Layout" : "",
    "LapTimeMs" : 109851,
    "WeatherStart" : "Clear",
    "WeatherEnd" : "Clear",
    "Track" : "ks_laguna_seca",
    "WeatherCategory" : "Clear",
    "TimestampMs" : 1774827827927,
    "SessionId" : "a0e48b87-bce6-4f92-af5e-279ba98811e9"
  },
  {
    "Car" : "bmw_z4_gt3",
    "SessionId" : "a0e48b87-bce6-4f92-af5e-279ba98811e9",
    "TimestampMs" : 1774828264239,
    "WeatherCategory" : "Clear",
    "Track" : "ks_laguna_seca",
    "WeatherEnd" : "Clear",
    "WeatherStart" : "Clear",
    "Layout" : "",
    "LapTimeMs" : 96186
  },
  {
    "Layout" : "",
    "LapTimeMs" : 89549,
    "WeatherStart" : "Clear",
    "WeatherEnd" : "Clear",
    "WeatherCategory" : "Clear",
    "Track" : "ks_laguna_seca",
    "SessionId" : "a0e48b87-bce6-4f92-af5e-279ba98811e9",
    "TimestampMs" : 1774828588487,
    "Car" : "bmw_z4_gt3"
  },
  {
    "WeatherCategory" : "Clear",
    "Track" : "ks_laguna_seca",
    "SessionId" : "a0e48b87-bce6-4f92-af5e-279ba98811e9",
    "TimestampMs" : 1774828995587,
    "Layout" : "",
    "LapTimeMs" : 90414,
    "WeatherStart" : "Clear",
    "WeatherEnd" : "Clear",
    "Car" : "bmw_z4_gt3"
  },
  {
    "WeatherStart" : "Clear",
    "Layout" : "",
    "LapTimeMs" : 98770,
    "WeatherEnd" : "Clear",
    "SessionId" : "a0e48b87-bce6-4f92-af5e-279ba98811e9",
    "TimestampMs" : 1774829094355,
    "Track" : "ks_laguna_seca",
    "WeatherCategory" : "Clear",
    "Car" : "bmw_z4_gt3"
  },
  {
    "Car" : "bmw_z4_gt3",
    "WeatherCategory" : "Clear",
    "Track" : "ks_laguna_seca",
    "SessionId" : "a0e48b87-bce6-4f92-af5e-279ba98811e9",
    "TimestampMs" : 1774829183062,
    "WeatherEnd" : "Clear",
    "Layout" : "",
    "LapTimeMs" : 88709,
    "WeatherStart" : "Clear"
  },
  {
    "WeatherEnd" : "Clear",
    "Layout" : "",
    "LapTimeMs" : 92338,
    "WeatherStart" : "Clear",
    "WeatherCategory" : "Clear",
    "Track" : "ks_laguna_seca",
    "SessionId" : "a0e48b87-bce6-4f92-af5e-279ba98811e9",
    "TimestampMs" : 1774829275399,
    "Car" : "bmw_z4_gt3"
  },
  {
    "WeatherEnd" : "Clear",
    "WeatherStart" : "Clear",
    "Layout" : "",
    "LapTimeMs" : 98943,
    "SessionId" : "a0e48b87-bce6-4f92-af5e-279ba98811e9",
    "TimestampMs" : 1774829374342,
    "Track" : "ks_laguna_seca",
    "WeatherCategory" : "Clear",
    "Car" : "bmw_z4_gt3"
  },
  {
    "SessionId" : "a0e48b87-bce6-4f92-af5e-279ba98811e9",
    "TimestampMs" : 1774829466238,
    "Track" : "ks_laguna_seca",
    "WeatherCategory" : "Clear",
    "WeatherStart" : "Clear",
    "LapTimeMs" : 91898,
    "Layout" : "",
    "WeatherEnd" : "Clear",
    "Car" : "bmw_z4_gt3"
  },
  {
    "WeatherCategory" : "Clear",
    "Track" : "ks_laguna_seca",
    "SessionId" : "a0e48b87-bce6-4f92-af5e-279ba98811e9",
    "TimestampMs" : 1774829555948,
    "LapTimeMs" : 89710,
    "Layout" : "",
    "WeatherStart" : "Clear",
    "WeatherEnd" : "Clear",
    "Car" : "bmw_z4_gt3"
  },
  {
    "Car" : "bmw_z4_gt3",
    "WeatherStart" : "Clear",
    "Layout" : "",
    "LapTimeMs" : 90248,
    "WeatherEnd" : "Clear",
    "TimestampMs" : 1774829646196,
    "SessionId" : "a0e48b87-bce6-4f92-af5e-279ba98811e9",
    "WeatherCategory" : "Clear",
    "Track" : "ks_laguna_seca"
  },
  {
    "Car" : "bmw_z4_gt3",
    "WeatherCategory" : "Clear",
    "Track" : "ks_laguna_seca",
    "TimestampMs" : 1774829737873,
    "SessionId" : "a0e48b87-bce6-4f92-af5e-279ba98811e9",
    "WeatherEnd" : "Clear",
    "LapTimeMs" : 91681,
    "Layout" : "",
    "WeatherStart" : "Clear"
  },
  {
    "Car" : "bmw_z4_gt3",
    "Track" : "ks_laguna_seca",
    "WeatherCategory" : "Clear",
    "SessionId" : "a0e48b87-bce6-4f92-af5e-279ba98811e9",
    "TimestampMs" : 1774829829235,
    "WeatherEnd" : "Clear",
    "Layout" : "",
    "LapTimeMs" : 91360,
    "WeatherStart" : "Clear"
  }
]
