[{"Layout":"gp","WeatherStart":"Clear","TimestampMs":1774758954000,"LapTimeMs":91541,"WeatherEnd":"Clear","SessionId":"c030ec2c-5b24-40de-8bfc-25c71ea11c59","WeatherCategory":"Clear","Track":"ks_brands_hatch","Car":"bmw_z4_gt3"},{"LapTimeMs":90076,"WeatherStart":"Clear","TimestampMs":1774759135935,"Layout":"gp","Track":"ks_brands_hatch","Car":"bmw_z4_gt3","SessionId":"c030ec2c-5b24-40de-8bfc-25c71ea11c59","WeatherCategory":"Clear","WeatherEnd":"Clear"},{"WeatherEnd":"Clear","WeatherCategory":"Clear","SessionId":"c030ec2c-5b24-40de-8bfc-25c71ea11c59","Car":"bmw_z4_gt3","Track":"ks_brands_hatch","Layout":"gp","TimestampMs":1774759370470,"WeatherStart":"Clear","LapTimeMs":90273},{"LapTimeMs":90210,"TimestampMs":1774759738765,"WeatherStart":"Clear","Layout":"gp","Car":"bmw_z4_gt3","Track":"ks_brands_hatch","WeatherCategory":"Clear","SessionId":"c030ec2c-5b24-40de-8bfc-25c71ea11c59","WeatherEnd":"Clear"},{"Car":"bmw_m3_gt2","Track":"ks_brands_hatch","WeatherEnd":"Clear","SessionId":"c030ec2c-5b24-40de-8bfc-25c71ea11c59","WeatherCategory":"Clear","TimestampMs":1774759739744,"WeatherStart":"Clear","LapTimeMs":86532,"Layout":"gp"},{"WeatherStart":"Clear","TimestampMs":1774759748674,"LapTimeMs":94368,"Layout":"gp","Track":"ks_brands_hatch","Car":"ferrari_458_gt2","WeatherEnd":"Clear","SessionId":"c030ec2c-5b24-40de-8bfc-25c71ea11c59","WeatherCategory":"Clear"},{"Track":"ks_brands_hatch","Car":"bmw_z4_gt3","SessionId":"c030ec2c-5b24-40de-8bfc-25c71ea11c59","WeatherCategory":"Clear","WeatherEnd":"Clear","LapTimeMs":103040,"WeatherStart":"Clear","TimestampMs":1774759754800,"Layout":"gp"},{"Layout":"gp","LapTimeMs":107525,"WeatherStart":"Clear","TimestampMs":1774759761963,"SessionId":"c030ec2c-5b24-40de-8bfc-25c71ea11c59","WeatherCategory":"Clear","WeatherEnd":"Clear","Track":"ks_brands_hatch","Car":"mclaren_mp412c_gt3"},{"Layout":"gp","LapTimeMs":107083,"WeatherStart":"Clear","TimestampMs":1774759769716,"SessionId":"c030ec2c-5b24-40de-8bfc-25c71ea11c59","WeatherCategory":"Clear","WeatherEnd":"Clear","Track":"ks_brands_hatch","Car":"mercedes_sls_gt3"},{"Track":"ks_brands_hatch","Car":"bmw_z4_gt3","WeatherEnd":"Clear","SessionId":"c030ec2c-5b24-40de-8bfc-25c71ea11c59","WeatherCategory":"Clear","WeatherStart":"Clear","TimestampMs":1774759829080,"LapTimeMs":90323,"Layout":"gp"},{"Layout":"gp","WeatherStart":"Clear","TimestampMs":1774759829725,"LapTimeMs":89982,"WeatherEnd":"Clear","SessionId":"c030ec2c-5b24-40de-8bfc-25c71ea11c59","WeatherCategory":"Clear","Track":"ks_brands_hatch","Car":"bmw_m3_gt2"},{"WeatherCategory":"Clear","SessionId":"c030ec2c-5b24-40de-8bfc-25c71ea11c59","WeatherEnd":"Clear","Car":"ferrari_458_gt2","Track":"ks_brands_hatch","Layout":"gp","LapTimeMs":94905,"TimestampMs":1774759843579,"WeatherStart":"Clear"},{"WeatherStart":"Clear","TimestampMs":1774759857698,"LapTimeMs":95736,"Layout":"gp","Track":"ks_brands_hatch","Car":"mclaren_mp412c_gt3","WeatherEnd":"Clear","SessionId":"c030ec2c-5b24-40de-8bfc-25c71ea11c59","WeatherCategory":"Clear"},{"WeatherEnd":"Clear","SessionId":"c030ec2c-5b24-40de-8bfc-25c71ea11c59","WeatherCategory":"Clear","Car":"mercedes_sls_gt3","Track":"ks_brands_hatch","Layout":"gp","TimestampMs":1774759875070,"WeatherStart":"Clear","LapTimeMs":105350},{"SessionId":"c030ec2c-5b24-40de-8bfc-25c71ea11c59","WeatherCategory":"Clear","WeatherEnd":"Clear","Car":"bmw_z4_gt3","Track":"ks_brands_hatch","Layout":"gp","LapTimeMs":97625,"TimestampMs":1774759926703,"WeatherStart":"Clear"},{"Track":"ks_brands_hatch","Car":"bmw_m3_gt2","WeatherCategory":"Clear","SessionId":"c030ec2c-5b24-40de-8bfc-25c71ea11c59","WeatherEnd":"Clear","LapTimeMs":97361,"WeatherStart":"Clear","TimestampMs":1774759927083,"Layout":"gp"},{"Layout":"gp","WeatherStart":"Clear","TimestampMs":1774759933990,"LapTimeMs":90409,"WeatherEnd":"Clear","WeatherCategory":"Clear","SessionId":"c030ec2c-5b24-40de-8bfc-25c71ea11c59","Track":"ks_brands_hatch","Car":"ferrari_458_gt2"},{"Track":"ks_brands_hatch","Car":"mclaren_mp412c_gt3","WeatherEnd":"Clear","SessionId":"c030ec2c-5b24-40de-8bfc-25c71ea11c59","WeatherCategory":"Clear","WeatherStart":"Clear","TimestampMs":1774759952231,"LapTimeMs":94535,"Layout":"gp"},{"Car":"mercedes_sls_gt3","Track":"ks_brands_hatch","WeatherCategory":"Clear","SessionId":"c030ec2c-5b24-40de-8bfc-25c71ea11c59","WeatherEnd":"Clear","LapTimeMs":98103,"TimestampMs":1774759973178,"WeatherStart":"Clear","Layout":"gp"},{"LapTimeMs":90131,"TimestampMs":1774760024118,"WeatherStart":"Clear","Layout":"gp","Car":"ferrari_458_gt2","Track":"ks_brands_hatch","WeatherCategory":"Clear","SessionId":"c030ec2c-5b24-40de-8bfc-25c71ea11c59","WeatherEnd":"Clear"},{"WeatherEnd":"Clear","SessionId":"c030ec2c-5b24-40de-8bfc-25c71ea11c59","WeatherCategory":"Clear","Track":"ks_brands_hatch","Car":"bmw_z4_gt3","Layout":"gp","WeatherStart":"Clear","TimestampMs":1774760024461,"LapTimeMs":97761},{"WeatherStart":"Clear","TimestampMs":1774760024949,"LapTimeMs":97868,"Layout":"gp","Track":"ks_brands_hatch","Car":"bmw_m3_gt2","WeatherEnd":"Clear","WeatherCategory":"Clear","SessionId":"c030ec2c-5b24-40de-8bfc-25c71ea11c59"},{"WeatherEnd":"Clear","SessionId":"c030ec2c-5b24-40de-8bfc-25c71ea11c59","WeatherCategory":"Clear","Car":"mclaren_mp412c_gt3","Track":"ks_brands_hatch","Layout":"gp","TimestampMs":1774760045116,"WeatherStart":"Clear","LapTimeMs":92887},{"Layout":"gp","TimestampMs":1774760069477,"WeatherStart":"Clear","LapTimeMs":96295,"WeatherEnd":"Clear","SessionId":"c030ec2c-5b24-40de-8bfc-25c71ea11c59","WeatherCategory":"Clear","Car":"mercedes_sls_gt3","Track":"ks_brands_hatch"},{"WeatherEnd":"Clear","WeatherCategory":"Clear","SessionId":"c030ec2c-5b24-40de-8bfc-25c71ea11c59","Car":"bmw_z4_gt3","Track":"ks_brands_hatch","Layout":"gp","TimestampMs":1774760113274,"WeatherStart":"Clear","LapTimeMs":88816},{"Car":"ferrari_458_gt2","Track":"ks_brands_hatch","SessionId":"c030ec2c-5b24-40de-8bfc-25c71ea11c59","WeatherCategory":"Clear","WeatherEnd":"Clear","LapTimeMs":94709,"TimestampMs":1774760118827,"WeatherStart":"Clear","Layout":"gp"},{"Layout":"gp","WeatherStart":"Clear","TimestampMs":1774760157897,"LapTimeMs":112784,"WeatherEnd":"Clear","SessionId":"c030ec2c-5b24-40de-8bfc-25c71ea11c59","WeatherCategory":"Clear","Track":"ks_brands_hatch","Car":"mclaren_mp412c_gt3"},{"Track":"ks_brands_hatch","Car":"mercedes_sls_gt3","SessionId":"c030ec2c-5b24-40de-8bfc-25c71ea11c59","WeatherCategory":"Clear","WeatherEnd":"Clear","LapTimeMs":95248,"WeatherStart":"Clear","TimestampMs":1774760164731,"Layout":"gp"},{"SessionId":"c030ec2c-5b24-40de-8bfc-25c71ea11c59","WeatherCategory":"Clear","WeatherEnd":"Clear","Car":"bmw_z4_gt3","Track":"ks_brands_hatch","Layout":"gp","LapTimeMs":90941,"TimestampMs":1774760204204,"WeatherStart":"Clear"},{"Car":"ferrari_458_gt2","Track":"ks_brands_hatch","WeatherEnd":"Clear","SessionId":"c030ec2c-5b24-40de-8bfc-25c71ea11c59","WeatherCategory":"Clear","TimestampMs":1774760208712,"WeatherStart":"Clear","LapTimeMs":89885,"Layout":"gp"},{"Track":"ks_brands_hatch","Car":"mclaren_mp412c_gt3","WeatherEnd":"Clear","SessionId":"c030ec2c-5b24-40de-8bfc-25c71ea11c59","WeatherCategory":"Clear","WeatherStart":"Clear","TimestampMs":1774760263910,"LapTimeMs":106014,"Layout":"gp"},{"WeatherEnd":"Clear","SessionId":"c030ec2c-5b24-40de-8bfc-25c71ea11c59","WeatherCategory":"Clear","Track":"ks_brands_hatch","Car":"mercedes_sls_gt3","Layout":"gp","WeatherStart":"Clear","TimestampMs":1774760268544,"LapTimeMs":103811},{"Track":"ks_brands_hatch","Car":"bmw_z4_gt3","WeatherEnd":"Clear","WeatherCategory":"Clear","SessionId":"c030ec2c-5b24-40de-8bfc-25c71ea11c59","WeatherStart":"Clear","TimestampMs":1774760297820,"LapTimeMs":93620,"Layout":"gp"},{"WeatherEnd":"Clear","WeatherCategory":"Clear","SessionId":"c030ec2c-5b24-40de-8bfc-25c71ea11c59","Car":"ferrari_458_gt2","Track":"ks_brands_hatch","Layout":"gp","TimestampMs":1774760299796,"WeatherStart":"Clear","LapTimeMs":91083},{"TimestampMs":1774760372330,"WeatherStart":"Clear","LapTimeMs":103781,"Layout":"gp","Car":"mercedes_sls_gt3","Track":"ks_brands_hatch","WeatherEnd":"Clear","SessionId":"c030ec2c-5b24-40de-8bfc-25c71ea11c59","WeatherCategory":"Clear"},{"WeatherEnd":"Clear","WeatherCategory":"Clear","SessionId":"c030ec2c-5b24-40de-8bfc-25c71ea11c59","Track":"ks_brands_hatch","Car":"mclaren_mp412c_gt3","Layout":"gp","WeatherStart":"Clear","TimestampMs":1774760389519,"LapTimeMs":125612},{"LapTimeMs":98549,"WeatherStart":"Clear","TimestampMs":1774760398345,"Layout":"gp","Track":"ks_brands_hatch","Car":"ferrari_458_gt2","SessionId":"c030ec2c-5b24-40de-8bfc-25c71ea11c59","WeatherCategory":"Clear","WeatherEnd":"Clear"},{"Track":"ks_brands_hatch","Car":"bmw_z4_gt3","WeatherEnd":"Clear","WeatherCategory":"Clear","SessionId":"c030ec2c-5b24-40de-8bfc-25c71ea11c59","WeatherStart":"Clear","TimestampMs":1774760410879,"LapTimeMs":113061,"Layout":"gp"},{"WeatherEnd":"Clear","WeatherCategory":"Clear","SessionId":"c030ec2c-5b24-40de-8bfc-25c71ea11c59","Car":"bmw_z4_gt3","Track":"ks_brands_hatch","Layout":"gp","TimestampMs":1774760484104,"WeatherStart":"Clear","LapTimeMs":94835},{"SessionId":"c030ec2c-5b24-40de-8bfc-25c71ea11c59","WeatherCategory":"Clear","WeatherEnd":"Clear","Track":"ks_brands_hatch","Car":"mercedes_sls_gt3","Layout":"gp","LapTimeMs":126551,"WeatherStart":"Clear","TimestampMs":1774760498885},{"Layout":"gp","TimestampMs":1774760501962,"WeatherStart":"Clear","LapTimeMs":91088,"WeatherEnd":"Clear","WeatherCategory":"Clear","SessionId":"c030ec2c-5b24-40de-8bfc-25c71ea11c59","Car":"bmw_z4_gt3","Track":"ks_brands_hatch"},{"Track":"ks_brands_hatch","Car":"ferrari_458_gt2","WeatherEnd":"Clear","SessionId":"c030ec2c-5b24-40de-8bfc-25c71ea11c59","WeatherCategory":"Clear","WeatherStart":"Clear","TimestampMs":1774760503771,"LapTimeMs":105424,"Layout":"gp"},{"Track":"ks_brands_hatch","Car":"mclaren_mp412c_gt3","WeatherCategory":"Clear","SessionId":"c030ec2c-5b24-40de-8bfc-25c71ea11c59","WeatherEnd":"Clear","LapTimeMs":115464,"WeatherStart":"Clear","TimestampMs":1774760504983,"Layout":"gp"},{"Layout":"gp","LapTimeMs":89153,"WeatherStart":"Clear","TimestampMs":1774760922930,"WeatherCategory":"Clear","SessionId":"c030ec2c-5b24-40de-8bfc-25c71ea11c59","WeatherEnd":"Clear","Track":"ks_brands_hatch","Car":"bmw_z4_gt3"},{"Car":"bmw_z4_gt3","Track":"ks_brands_hatch","WeatherEnd":"Clear","SessionId":"c030ec2c-5b24-40de-8bfc-25c71ea11c59","WeatherCategory":"Clear","TimestampMs":1774761013164,"WeatherStart":"Clear","LapTimeMs":90237,"Layout":"gp"},{"Car":"bmw_z4_gt3","Track":"ks_brands_hatch","SessionId":"c030ec2c-5b24-40de-8bfc-25c71ea11c59","WeatherCategory":"Clear","WeatherEnd":"Clear","LapTimeMs":88856,"TimestampMs":1774761102016,"WeatherStart":"Clear","Layout":"gp"},{"WeatherCategory":"Clear","SessionId":"c030ec2c-5b24-40de-8bfc-25c71ea11c59","WeatherEnd":"Clear","Car":"bmw_z4_gt3","Track":"ks_brands_hatch","Layout":"gp","LapTimeMs":92206,"TimestampMs":1774761302401,"WeatherStart":"Clear"},{"Track":"ks_brands_hatch","Car":"bmw_z4_gt3","WeatherEnd":"Clear","SessionId":"c030ec2c-5b24-40de-8bfc-25c71ea11c59","WeatherCategory":"Clear","WeatherStart":"Clear","TimestampMs":1774761390899,"LapTimeMs":88498,"Layout":"gp"},{"Track":"ks_brands_hatch","Car":"bmw_z4_gt3","WeatherCategory":"Clear","SessionId":"ec7420b4-0ffe-4e8a-81f4-d1fb4aacccd6","WeatherEnd":"Clear","LapTimeMs":87743,"WeatherStart":"Clear","TimestampMs":1774796547238,"Layout":"gp"},{"WeatherStart":"Clear","TimestampMs":1774796633958,"LapTimeMs":86726,"Layout":"gp","Track":"ks_brands_hatch","Car":"bmw_z4_gt3","WeatherEnd":"Clear","SessionId":"ec7420b4-0ffe-4e8a-81f4-d1fb4aacccd6","WeatherCategory":"Clear"},{"Layout":"gp","WeatherStart":"Clear","TimestampMs":1774796810427,"LapTimeMs":86826,"WeatherEnd":"Clear","SessionId":"ec7420b4-0ffe-4e8a-81f4-d1fb4aacccd6","WeatherCategory":"Clear","Track":"ks_brands_hatch","Car":"bmw_z4_gt3"}]