[
  {
    "TimestampMs": 1776704103567,
    "SessionId": "b21333f1-04ad-47d9-82d5-3b45f191f730",
    "Track": "spa",
    "Layout": "",
    "Car": "bmw_z4_gt3",
    "LapTimeMs": 148161,
    "WeatherCategory": "Clear",
    "WeatherStart": "Clear",
    "WeatherEnd": "Clear"
  },
  {
    "TimestampMs": 1776704393191,
    "SessionId": "b21333f1-04ad-47d9-82d5-3b45f191f730",
    "Track": "spa",
    "Layout": "",
    "Car": "bmw_z4_gt3",
    "LapTimeMs": 144367,
    "WeatherCategory": "Clear",
    "WeatherStart": "Clear",
    "WeatherEnd": "Clear"
  }
]