[{"Layout":"","LapTimeMs":153803,"WeatherStart":"Clear","TimestampMs":1775348848674,"SessionId":"ea64fae3-50ef-449d-bb65-73ac08bbe881","WeatherCategory":"Clear","WeatherEnd":"Clear","Track":"spa","Car":"mercedes_sls_gt3"},{"Layout":"","LapTimeMs":150833,"WeatherStart":"Clear","TimestampMs":1775348999504,"SessionId":"ea64fae3-50ef-449d-bb65-73ac08bbe881","WeatherCategory":"Clear","WeatherEnd":"Clear","Track":"spa","Car":"mercedes_sls_gt3"},{"LapTimeMs":175052,"TimestampMs":1775349174555,"WeatherStart":"Clear","Layout":"","Car":"mercedes_sls_gt3","Track":"spa","SessionId":"ea64fae3-50ef-449d-bb65-73ac08bbe881","WeatherCategory":"Clear","WeatherEnd":"Clear"},{"WeatherEnd":"Clear","SessionId":"ea64fae3-50ef-449d-bb65-73ac08bbe881","WeatherCategory":"Clear","Car":"mercedes_sls_gt3","Track":"spa","Layout":"","TimestampMs":1775349344373,"WeatherStart":"Clear","LapTimeMs":169823},{"WeatherEnd":"Clear","SessionId":"ea64fae3-50ef-449d-bb65-73ac08bbe881","WeatherCategory":"Clear","Track":"spa","Car":"mercedes_sls_gt3","Layout":"","WeatherStart":"Clear","TimestampMs":1775350587106,"LapTimeMs":158892},{"Car":"mercedes_sls_gt3","Track":"spa","WeatherCategory":"Clear","SessionId":"ea64fae3-50ef-449d-bb65-73ac08bbe881","WeatherEnd":"Clear","LapTimeMs":148908,"TimestampMs":1775350907099,"WeatherStart":"Clear","Layout":""},{"WeatherEnd":"Clear","SessionId":"ea64fae3-50ef-449d-bb65-73ac08bbe881","WeatherCategory":"Clear","Track":"spa","Car":"mercedes_sls_gt3","Layout":"","WeatherStart":"Clear","TimestampMs":1775351064102,"LapTimeMs":157004},{"Car":"ferrari_458_gt2","Track":"spa","WeatherEnd":"Clear","WeatherCategory":"Clear","SessionId":"ea64fae3-50ef-449d-bb65-73ac08bbe881","TimestampMs":1775352565607,"WeatherStart":"Clear","LapTimeMs":147369,"Layout":""},{"Layout":"","LapTimeMs":146974,"WeatherStart":"Clear","TimestampMs":1775352712579,"WeatherCategory":"Clear","SessionId":"ea64fae3-50ef-449d-bb65-73ac08bbe881","WeatherEnd":"Clear","Track":"spa","Car":"ferrari_458_gt2"},{"Track":"spa","Car":"ferrari_458_gt2","WeatherEnd":"Clear","SessionId":"ea64fae3-50ef-449d-bb65-73ac08bbe881","WeatherCategory":"Clear","WeatherStart":"Clear","TimestampMs":1775352874653,"LapTimeMs":162077,"Layout":""},{"TimestampMs":1775353027308,"WeatherStart":"Clear","LapTimeMs":152656,"Layout":"","Car":"ferrari_458_gt2","Track":"spa","WeatherEnd":"Clear","SessionId":"ea64fae3-50ef-449d-bb65-73ac08bbe881","WeatherCategory":"Clear"},{"Track":"spa","Car":"ferrari_458_gt2","WeatherEnd":"Clear","SessionId":"ea64fae3-50ef-449d-bb65-73ac08bbe881","WeatherCategory":"Clear","WeatherStart":"Clear","TimestampMs":1775353179115,"LapTimeMs":151809,"Layout":""},{"WeatherStart":"Clear","TimestampMs":1775353733713,"LapTimeMs":144778,"Layout":"","Track":"spa","Car":"ferrari_458_gt2","WeatherEnd":"Clear","SessionId":"ea64fae3-50ef-449d-bb65-73ac08bbe881","WeatherCategory":"Clear"},{"WeatherEnd":"Clear","WeatherCategory":"Clear","SessionId":"ea64fae3-50ef-449d-bb65-73ac08bbe881","Track":"spa","Car":"ferrari_458_gt2","Layout":"","WeatherStart":"Clear","TimestampMs":1775353879622,"LapTimeMs":145913}]