[{"Layout":"","LapTimeMs":116921,"WeatherStart":"Clear","TimestampMs":1774916362855,"WeatherCategory":"Clear","SessionId":"1f2afa3d-8e6e-4012-98e4-f29d53e60f7d","WeatherEnd":"Clear","Track":"monza","Car":"mercedes_sls_gt3"},{"WeatherStart":"Clear","TimestampMs":1774916479403,"LapTimeMs":116548,"Layout":"","Track":"monza","Car":"mercedes_sls_gt3","WeatherEnd":"Clear","WeatherCategory":"Clear","SessionId":"1f2afa3d-8e6e-4012-98e4-f29d53e60f7d"},{"LapTimeMs":141351,"TimestampMs":1774916620755,"WeatherStart":"Clear","Layout":"","Car":"mercedes_sls_gt3","Track":"monza","SessionId":"1f2afa3d-8e6e-4012-98e4-f29d53e60f7d","WeatherCategory":"Clear","WeatherEnd":"Clear"},{"WeatherEnd":"Clear","SessionId":"1f2afa3d-8e6e-4012-98e4-f29d53e60f7d","WeatherCategory":"Clear","Track":"monza","Car":"mercedes_sls_gt3","Layout":"","WeatherStart":"Clear","TimestampMs":1774916743219,"LapTimeMs":122463},{"Layout":"","TimestampMs":1774917348226,"WeatherStart":"Clear","LapTimeMs":116696,"WeatherEnd":"Clear","WeatherCategory":"Clear","SessionId":"1f2afa3d-8e6e-4012-98e4-f29d53e60f7d","Car":"mercedes_sls_gt3","Track":"monza"},{"WeatherCategory":"Clear","SessionId":"1f2afa3d-8e6e-4012-98e4-f29d53e60f7d","WeatherEnd":"Clear","Car":"mercedes_sls_gt3","Track":"monza","Layout":"","LapTimeMs":137570,"TimestampMs":1774918141581,"WeatherStart":"Clear"},{"LapTimeMs":129314,"WeatherStart":"Clear","TimestampMs":1774918270894,"Layout":"","Track":"monza","Car":"mercedes_sls_gt3","WeatherCategory":"Clear","SessionId":"1f2afa3d-8e6e-4012-98e4-f29d53e60f7d","WeatherEnd":"Clear"},{"Layout":"","LapTimeMs":116121,"WeatherStart":"Clear","TimestampMs":1774918387016,"SessionId":"1f2afa3d-8e6e-4012-98e4-f29d53e60f7d","WeatherCategory":"Clear","WeatherEnd":"Clear","Track":"monza","Car":"mercedes_sls_gt3"},{"LapTimeMs":117701,"WeatherStart":"Clear","TimestampMs":1774918504721,"Layout":"","Track":"monza","Car":"mercedes_sls_gt3","SessionId":"1f2afa3d-8e6e-4012-98e4-f29d53e60f7d","WeatherCategory":"Clear","WeatherEnd":"Clear"}]