[
  {
    "WeatherEnd" : "Clear",
    "WeatherStart" : "Clear",
    "LapTimeMs" : 144289,
    "Layout" : "",
    "TimestampMs" : 1774920560233,
    "SessionId" : "ebde6d69-1632-458e-9560-0d5502d5205f",
    "WeatherCategory" : "Clear",
    "Track" : "spa",
    "Car" : "ferrari_458_gt2"
  },
  {
    "Car" : "ferrari_458_gt2",
    "WeatherCategory" : "Clear",
    "Track" : "spa",
    "TimestampMs" : 1774920703424,
    "SessionId" : "ebde6d69-1632-458e-9560-0d5502d5205f",
    "LapTimeMs" : 143186,
    "Layout" : "",
    "WeatherStart" : "Clear",
    "WeatherEnd" : "Clear"
  },
  {
    "LapTimeMs" : 141957,
    "Layout" : "",
    "WeatherStart" : "Clear",
    "WeatherEnd" : "Clear",
    "Track" : "spa",
    "WeatherCategory" : "Clear",
    "SessionId" : "ebde6d69-1632-458e-9560-0d5502d5205f",
    "TimestampMs" : 1774921447840,
    "Car" : "ferrari_458_gt2"
  },
  {
    "WeatherEnd" : "Clear",
    "Layout" : "",
    "LapTimeMs" : 141407,
    "WeatherStart" : "Clear",
    "WeatherCategory" : "Clear",
    "Track" : "spa",
    "SessionId" : "ebde6d69-1632-458e-9560-0d5502d5205f",
    "TimestampMs" : 1774921589253,
    "Car" : "ferrari_458_gt2"
  },
  {
    "Track" : "spa",
    "WeatherCategory" : "Clear",
    "SessionId" : "ebde6d69-1632-458e-9560-0d5502d5205f",
    "TimestampMs" : 1774922138045,
    "LapTimeMs" : 142386,
    "Layout" : "",
    "WeatherStart" : "Clear",
    "WeatherEnd" : "Clear",
    "Car" : "ferrari_458_gt2"
  }
]
