[
  {
    "TimestampMs": 1778294667375,
    "SessionId": "c182c0f8-0a99-49e9-a029-69f64f413053",
    "Track": "ks_silverstone",
    "Layout": "gp",
    "Car": "ferrari_458_gt2",
    "LapTimeMs": 158587,
    "WeatherCategory": "Clear",
    "WeatherStart": "Clear",
    "WeatherEnd": "Clear"
  },
  {
    "TimestampMs": 1778294812861,
    "SessionId": "c182c0f8-0a99-49e9-a029-69f64f413053",
    "Track": "ks_silverstone",
    "Layout": "gp",
    "Car": "ferrari_458_gt2",
    "LapTimeMs": 145482,
    "WeatherCategory": "Clear",
    "WeatherStart": "Clear",
    "WeatherEnd": "Clear"
  },
  {
    "TimestampMs": 1778294940836,
    "SessionId": "c182c0f8-0a99-49e9-a029-69f64f413053",
    "Track": "ks_silverstone",
    "Layout": "gp",
    "Car": "ferrari_458_gt2",
    "LapTimeMs": 127971,
    "WeatherCategory": "Clear",
    "WeatherStart": "Clear",
    "WeatherEnd": "Clear"
  },
  {
    "TimestampMs": 1778295069033,
    "SessionId": "c182c0f8-0a99-49e9-a029-69f64f413053",
    "Track": "ks_silverstone",
    "Layout": "gp",
    "Car": "ferrari_458_gt2",
    "LapTimeMs": 128196,
    "WeatherCategory": "Clear",
    "WeatherStart": "Clear",
    "WeatherEnd": "Clear"
  },
  {
    "TimestampMs": 1778295195130,
    "SessionId": "c182c0f8-0a99-49e9-a029-69f64f413053",
    "Track": "ks_silverstone",
    "Layout": "gp",
    "Car": "ferrari_458_gt2",
    "LapTimeMs": 126094,
    "WeatherCategory": "Clear",
    "WeatherStart": "Clear",
    "WeatherEnd": "Clear"
  },
  {
    "TimestampMs": 1778295900295,
    "SessionId": "c182c0f8-0a99-49e9-a029-69f64f413053",
    "Track": "ks_silverstone",
    "Layout": "gp",
    "Car": "ferrari_458_gt2",
    "LapTimeMs": 126262,
    "WeatherCategory": "Clear",
    "WeatherStart": "Clear",
    "WeatherEnd": "Clear"
  },
  {
    "TimestampMs": 1778296030464,
    "SessionId": "c182c0f8-0a99-49e9-a029-69f64f413053",
    "Track": "ks_silverstone",
    "Layout": "gp",
    "Car": "ferrari_458_gt2",
    "LapTimeMs": 130168,
    "WeatherCategory": "Clear",
    "WeatherStart": "Clear",
    "WeatherEnd": "Clear"
  },
  {
    "TimestampMs": 1778296156214,
    "SessionId": "c182c0f8-0a99-49e9-a029-69f64f413053",
    "Track": "ks_silverstone",
    "Layout": "gp",
    "Car": "ferrari_458_gt2",
    "LapTimeMs": 125749,
    "WeatherCategory": "Clear",
    "WeatherStart": "Clear",
    "WeatherEnd": "Clear"
  },
  {
    "TimestampMs": 1778296282764,
    "SessionId": "c182c0f8-0a99-49e9-a029-69f64f413053",
    "Track": "ks_silverstone",
    "Layout": "gp",
    "Car": "ferrari_458_gt2",
    "LapTimeMs": 126546,
    "WeatherCategory": "Clear",
    "WeatherStart": "Clear",
    "WeatherEnd": "Clear"
  },
  {
    "TimestampMs": 1778296408020,
    "SessionId": "c182c0f8-0a99-49e9-a029-69f64f413053",
    "Track": "ks_silverstone",
    "Layout": "gp",
    "Car": "ferrari_458_gt2",
    "LapTimeMs": 125253,
    "WeatherCategory": "Clear",
    "WeatherStart": "Clear",
    "WeatherEnd": "Clear"
  },
  {
    "TimestampMs": 1778296534478,
    "SessionId": "c182c0f8-0a99-49e9-a029-69f64f413053",
    "Track": "ks_silverstone",
    "Layout": "gp",
    "Car": "ferrari_458_gt2",
    "LapTimeMs": 126454,
    "WeatherCategory": "Clear",
    "WeatherStart": "Clear",
    "WeatherEnd": "Clear"
  },
  {
    "TimestampMs": 1778297189281,
    "SessionId": "c182c0f8-0a99-49e9-a029-69f64f413053",
    "Track": "ks_silverstone",
    "Layout": "gp",
    "Car": "ferrari_458_gt2",
    "LapTimeMs": 125421,
    "WeatherCategory": "Clear",
    "WeatherStart": "Clear",
    "WeatherEnd": "Clear"
  },
  {
    "TimestampMs": 1778297313589,
    "SessionId": "c182c0f8-0a99-49e9-a029-69f64f413053",
    "Track": "ks_silverstone",
    "Layout": "gp",
    "Car": "ferrari_458_gt2",
    "LapTimeMs": 124307,
    "WeatherCategory": "Clear",
    "WeatherStart": "Clear",
    "WeatherEnd": "Clear"
  },
  {
    "TimestampMs": 1778297437921,
    "SessionId": "c182c0f8-0a99-49e9-a029-69f64f413053",
    "Track": "ks_silverstone",
    "Layout": "gp",
    "Car": "ferrari_458_gt2",
    "LapTimeMs": 124329,
    "WeatherCategory": "Clear",
    "WeatherStart": "Clear",
    "WeatherEnd": "Clear"
  },
  {
    "TimestampMs": 1778297571427,
    "SessionId": "c182c0f8-0a99-49e9-a029-69f64f413053",
    "Track": "ks_silverstone",
    "Layout": "gp",
    "Car": "ferrari_458_gt2",
    "LapTimeMs": 133505,
    "WeatherCategory": "Clear",
    "WeatherStart": "Clear",
    "WeatherEnd": "Clear"
  },
  {
    "TimestampMs": 1778297698315,
    "SessionId": "c182c0f8-0a99-49e9-a029-69f64f413053",
    "Track": "ks_silverstone",
    "Layout": "gp",
    "Car": "ferrari_458_gt2",
    "LapTimeMs": 126885,
    "WeatherCategory": "Clear",
    "WeatherStart": "Clear",
    "WeatherEnd": "Clear"
  },
  {
    "TimestampMs": 1778297826826,
    "SessionId": "c182c0f8-0a99-49e9-a029-69f64f413053",
    "Track": "ks_silverstone",
    "Layout": "gp",
    "Car": "ferrari_458_gt2",
    "LapTimeMs": 128510,
    "WeatherCategory": "Clear",
    "WeatherStart": "Clear",
    "WeatherEnd": "Clear"
  },
  {
    "TimestampMs": 1778298067430,
    "SessionId": "c182c0f8-0a99-49e9-a029-69f64f413053",
    "Track": "ks_silverstone",
    "Layout": "gp",
    "Car": "ferrari_458_gt2",
    "LapTimeMs": 240600,
    "WeatherCategory": "Clear",
    "WeatherStart": "Clear",
    "WeatherEnd": "Clear"
  }
]