[{"WeatherStart":"Clear","TimestampMs":1775002029457,"LapTimeMs":133373,"Layout":"gp","Track":"ks_silverstone","Car":"ferrari_458_gt2","WeatherEnd":"Clear","WeatherCategory":"Clear","SessionId":"28138f39-b1a3-4baf-947d-b2aed0783c42"},{"WeatherStart":"Clear","TimestampMs":1775009589753,"LapTimeMs":151779,"Layout":"gp","Track":"ks_silverstone","Car":"bmw_z4_gt3","WeatherEnd":"Clear","SessionId":"28138f39-b1a3-4baf-947d-b2aed0783c42","WeatherCategory":"Clear"},{"WeatherStart":"Clear","TimestampMs":1775009742934,"LapTimeMs":153207,"Layout":"gp","Track":"ks_silverstone","Car":"bmw_z4_gt3","WeatherEnd":"Clear","WeatherCategory":"Clear","SessionId":"28138f39-b1a3-4baf-947d-b2aed0783c42"},{"Track":"ks_silverstone","Car":"bmw_z4_gt3","WeatherEnd":"Clear","SessionId":"28138f39-b1a3-4baf-947d-b2aed0783c42","WeatherCategory":"Clear","WeatherStart":"Clear","TimestampMs":1775009895556,"LapTimeMs":152621,"Layout":"gp"},{"Layout":"gp","WeatherStart":"Clear","TimestampMs":1775010043929,"LapTimeMs":148372,"WeatherEnd":"Clear","SessionId":"28138f39-b1a3-4baf-947d-b2aed0783c42","WeatherCategory":"Clear","Track":"ks_silverstone","Car":"bmw_z4_gt3"},{"Layout":"gp","TimestampMs":1775164269474,"WeatherStart":"Clear","LapTimeMs":124967,"WeatherEnd":"Clear","WeatherCategory":"Clear","SessionId":"48a47624-87f0-4884-9099-d5b3182f650e","Car":"bmw_z4_gt3","Track":"ks_silverstone"},{"Track":"ks_silverstone","Car":"bmw_z4_gt3","WeatherEnd":"Clear","SessionId":"48a47624-87f0-4884-9099-d5b3182f650e","WeatherCategory":"Clear","WeatherStart":"Clear","TimestampMs":1775164608748,"LapTimeMs":124108,"Layout":"gp"},{"Car":"bmw_z4_gt3","Track":"ks_silverstone","WeatherEnd":"Clear","SessionId":"48a47624-87f0-4884-9099-d5b3182f650e","WeatherCategory":"Clear","TimestampMs":1775164735276,"WeatherStart":"Clear","LapTimeMs":126532,"Layout":"gp"},{"WeatherStart":"Clear","TimestampMs":1775165690989,"LapTimeMs":128329,"Layout":"gp","Track":"ks_silverstone","Car":"bmw_z4_gt3","WeatherEnd":"Clear","SessionId":"48a47624-87f0-4884-9099-d5b3182f650e","WeatherCategory":"Clear"},{"WeatherEnd":"Clear","WeatherCategory":"Clear","SessionId":"48a47624-87f0-4884-9099-d5b3182f650e","Car":"bmw_z4_gt3","Track":"ks_silverstone","Layout":"gp","TimestampMs":1775165692380,"WeatherStart":"Clear","LapTimeMs":129855},{"WeatherEnd":"Clear","SessionId":"48a47624-87f0-4884-9099-d5b3182f650e","WeatherCategory":"Clear","Track":"ks_silverstone","Car":"bmw_z4_gt3","Layout":"gp","WeatherStart":"Clear","TimestampMs":1775165816453,"LapTimeMs":125466},{"WeatherStart":"Clear","TimestampMs":1775165930393,"LapTimeMs":127852,"Layout":"gp","Track":"ks_silverstone","Car":"ferrari_458_gt2","WeatherEnd":"Clear","SessionId":"48a47624-87f0-4884-9099-d5b3182f650e","WeatherCategory":"Clear"},{"Car":"mercedes_sls_gt3","Track":"ks_silverstone","WeatherEnd":"Clear","WeatherCategory":"Clear","SessionId":"48a47624-87f0-4884-9099-d5b3182f650e","TimestampMs":1775166159309,"WeatherStart":"Clear","LapTimeMs":124355,"Layout":"gp"},{"WeatherStart":"Clear","TimestampMs":1775166282157,"LapTimeMs":122852,"Layout":"gp","Track":"ks_silverstone","Car":"mercedes_sls_gt3","WeatherEnd":"Clear","SessionId":"48a47624-87f0-4884-9099-d5b3182f650e","WeatherCategory":"Clear"},{"WeatherEnd":"Clear","SessionId":"48a47624-87f0-4884-9099-d5b3182f650e","WeatherCategory":"Clear","Track":"ks_silverstone","Car":"bmw_z4_gt3","Layout":"gp","WeatherStart":"Clear","TimestampMs":1775166566717,"LapTimeMs":127741},{"Layout":"gp","WeatherStart":"Clear","TimestampMs":1775166693577,"LapTimeMs":126860,"WeatherEnd":"Clear","WeatherCategory":"Clear","SessionId":"48a47624-87f0-4884-9099-d5b3182f650e","Track":"ks_silverstone","Car":"bmw_z4_gt3"},{"Track":"ks_silverstone","Car":"bmw_z4_gt3","SessionId":"48a47624-87f0-4884-9099-d5b3182f650e","WeatherCategory":"Clear","WeatherEnd":"Clear","LapTimeMs":126367,"WeatherStart":"Clear","TimestampMs":1775166819959,"Layout":"gp"},{"WeatherEnd":"Clear","WeatherCategory":"Clear","SessionId":"48a47624-87f0-4884-9099-d5b3182f650e","Car":"bmw_z4_gt3","Track":"ks_silverstone","Layout":"gp","TimestampMs":1775166946650,"WeatherStart":"Clear","LapTimeMs":126699},{"Car":"bmw_z4_gt3","Track":"ks_silverstone","WeatherCategory":"Clear","SessionId":"48a47624-87f0-4884-9099-d5b3182f650e","WeatherEnd":"Clear","LapTimeMs":127564,"TimestampMs":1775167202146,"WeatherStart":"Clear","Layout":"gp"},{"LapTimeMs":126699,"TimestampMs":1775167328845,"WeatherStart":"Clear","Layout":"gp","Car":"bmw_z4_gt3","Track":"ks_silverstone","WeatherCategory":"Clear","SessionId":"48a47624-87f0-4884-9099-d5b3182f650e","WeatherEnd":"Clear"},{"WeatherEnd":"Clear","WeatherCategory":"Clear","SessionId":"48a47624-87f0-4884-9099-d5b3182f650e","Track":"ks_silverstone","Car":"bmw_z4_gt3","Layout":"gp","WeatherStart":"Clear","TimestampMs":1775167589492,"LapTimeMs":125924},{"Car":"bmw_z4_gt3","Track":"ks_silverstone","SessionId":"48a47624-87f0-4884-9099-d5b3182f650e","WeatherCategory":"Clear","WeatherEnd":"Clear","LapTimeMs":126350,"TimestampMs":1775167887390,"WeatherStart":"Clear","Layout":"gp"},{"WeatherEnd":"Clear","SessionId":"48a47624-87f0-4884-9099-d5b3182f650e","WeatherCategory":"Clear","Car":"bmw_z4_gt3","Track":"ks_silverstone","Layout":"gp","TimestampMs":1775168013691,"WeatherStart":"Clear","LapTimeMs":126300},{"LapTimeMs":127395,"TimestampMs":1775168141087,"WeatherStart":"Clear","Layout":"gp","Car":"bmw_z4_gt3","Track":"ks_silverstone","SessionId":"48a47624-87f0-4884-9099-d5b3182f650e","WeatherCategory":"Clear","WeatherEnd":"Clear"},{"Car":"bmw_z4_gt3","Track":"ks_silverstone","SessionId":"48a47624-87f0-4884-9099-d5b3182f650e","WeatherCategory":"Clear","WeatherEnd":"Clear","LapTimeMs":127157,"TimestampMs":1775168394320,"WeatherStart":"Clear","Layout":"gp"},{"WeatherStart":"Clear","TimestampMs":1775168521002,"LapTimeMs":126677,"Layout":"gp","Track":"ks_silverstone","Car":"bmw_z4_gt3","WeatherEnd":"Clear","SessionId":"48a47624-87f0-4884-9099-d5b3182f650e","WeatherCategory":"Clear"},{"WeatherEnd":"Clear","WeatherCategory":"Clear","SessionId":"fead758f-db81-4a97-ab41-0911bc23bec6","Car":"mercedes_sls_gt3","Track":"ks_silverstone","Layout":"gp","TimestampMs":1775226016244,"WeatherStart":"Clear","LapTimeMs":131486},{"WeatherCategory":"Clear","SessionId":"002b81d4-2a2b-4a35-8b61-aaed99dd1662","WeatherEnd":"Clear","Track":"ks_silverstone","Car":"bmw_z4_gt3","Layout":"gp","LapTimeMs":131859,"WeatherStart":"Clear","TimestampMs":1775407303513},{"Layout":"gp","LapTimeMs":143165,"WeatherStart":"Clear","TimestampMs":1775408110414,"WeatherCategory":"Clear","SessionId":"002b81d4-2a2b-4a35-8b61-aaed99dd1662","WeatherEnd":"Clear","Track":"ks_silverstone","Car":"bmw_z4_gt3"},{"Car":"bmw_z4_gt3","Track":"ks_silverstone","WeatherCategory":"Clear","SessionId":"002b81d4-2a2b-4a35-8b61-aaed99dd1662","WeatherEnd":"Clear","LapTimeMs":133252,"TimestampMs":1775408243659,"WeatherStart":"Clear","Layout":"gp"},{"WeatherEnd":"Clear","SessionId":"002b81d4-2a2b-4a35-8b61-aaed99dd1662","WeatherCategory":"Clear","Track":"ks_silverstone","Car":"bmw_z4_gt3","Layout":"gp","WeatherStart":"Clear","TimestampMs":1775408373615,"LapTimeMs":129966},{"Layout":"gp","LapTimeMs":129874,"WeatherStart":"Clear","TimestampMs":1775408503465,"WeatherCategory":"Clear","SessionId":"002b81d4-2a2b-4a35-8b61-aaed99dd1662","WeatherEnd":"Clear","Track":"ks_silverstone","Car":"bmw_z4_gt3"},{"SessionId":"002b81d4-2a2b-4a35-8b61-aaed99dd1662","WeatherCategory":"Clear","WeatherEnd":"Clear","Track":"ks_silverstone","Car":"bmw_z4_gt3","Layout":"gp","LapTimeMs":131032,"WeatherStart":"Clear","TimestampMs":1775408634490},{"LapTimeMs":129592,"TimestampMs":1775409024815,"WeatherStart":"Clear","Layout":"gp","Car":"bmw_z4_gt3","Track":"ks_silverstone","SessionId":"002b81d4-2a2b-4a35-8b61-aaed99dd1662","WeatherCategory":"Clear","WeatherEnd":"Clear"},{"SessionId":"002b81d4-2a2b-4a35-8b61-aaed99dd1662","WeatherCategory":"Clear","WeatherEnd":"Clear","Car":"bmw_z4_gt3","Track":"ks_silverstone","Layout":"gp","LapTimeMs":128509,"TimestampMs":1775409289229,"WeatherStart":"Clear"},{"Layout":"gp","WeatherStart":"Clear","TimestampMs":1775413562400,"LapTimeMs":143881,"WeatherEnd":"Clear","SessionId":"002b81d4-2a2b-4a35-8b61-aaed99dd1662","WeatherCategory":"Clear","Track":"ks_silverstone","Car":"bmw_z4_gt3"},{"WeatherCategory":"Clear","SessionId":"002b81d4-2a2b-4a35-8b61-aaed99dd1662","WeatherEnd":"Clear","Car":"bmw_z4_gt3","Track":"ks_silverstone","Layout":"gp","LapTimeMs":143164,"TimestampMs":1775424429995,"WeatherStart":"Clear"},{"WeatherCategory":"Clear","SessionId":"002b81d4-2a2b-4a35-8b61-aaed99dd1662","WeatherEnd":"Clear","Track":"ks_silverstone","Car":"bmw_z4_gt3","Layout":"gp","LapTimeMs":140559,"WeatherStart":"Clear","TimestampMs":1775424570560}]