[
  {
    "TimestampMs": 1776711225785,
    "SessionId": "b21333f1-04ad-47d9-82d5-3b45f191f730",
    "Track": "spa",
    "Layout": "",
    "Car": "bmw_z4_gt3",
    "LapTimeMs": 150537,
    "WeatherCategory": "Clear",
    "WeatherStart": "Clear",
    "WeatherEnd": "Clear"
  },
  {
    "TimestampMs": 1776711882922,
    "SessionId": "b21333f1-04ad-47d9-82d5-3b45f191f730",
    "Track": "spa",
    "Layout": "",
    "Car": "bmw_z4_gt3",
    "LapTimeMs": 151888,
    "WeatherCategory": "Clear",
    "WeatherStart": "Clear",
    "WeatherEnd": "Clear"
  },
  {
    "TimestampMs": 1776712261028,
    "SessionId": "b21333f1-04ad-47d9-82d5-3b45f191f730",
    "Track": "spa",
    "Layout": "",
    "Car": "bmw_z4_gt3",
    "LapTimeMs": 150882,
    "WeatherCategory": "Clear",
    "WeatherStart": "Clear",
    "WeatherEnd": "Clear"
  },
  {
    "TimestampMs": 1776712413902,
    "SessionId": "b21333f1-04ad-47d9-82d5-3b45f191f730",
    "Track": "spa",
    "Layout": "",
    "Car": "bmw_z4_gt3",
    "LapTimeMs": 152874,
    "WeatherCategory": "Clear",
    "WeatherStart": "Clear",
    "WeatherEnd": "Clear"
  },
  {
    "TimestampMs": 1776712578460,
    "SessionId": "b21333f1-04ad-47d9-82d5-3b45f191f730",
    "Track": "spa",
    "Layout": "",
    "Car": "bmw_z4_gt3",
    "LapTimeMs": 164560,
    "WeatherCategory": "Clear",
    "WeatherStart": "Clear",
    "WeatherEnd": "Clear"
  },
  {
    "TimestampMs": 1776712732457,
    "SessionId": "b21333f1-04ad-47d9-82d5-3b45f191f730",
    "Track": "spa",
    "Layout": "",
    "Car": "bmw_z4_gt3",
    "LapTimeMs": 154000,
    "WeatherCategory": "Clear",
    "WeatherStart": "Clear",
    "WeatherEnd": "Clear"
  },
  {
    "TimestampMs": 1776712906311,
    "SessionId": "b21333f1-04ad-47d9-82d5-3b45f191f730",
    "Track": "spa",
    "Layout": "",
    "Car": "bmw_z4_gt3",
    "LapTimeMs": 173854,
    "WeatherCategory": "Clear",
    "WeatherStart": "Clear",
    "WeatherEnd": "Clear"
  },
  {
    "TimestampMs": 1776713681325,
    "SessionId": "b21333f1-04ad-47d9-82d5-3b45f191f730",
    "Track": "spa",
    "Layout": "",
    "Car": "bmw_z4_gt3",
    "LapTimeMs": 155077,
    "WeatherCategory": "Clear",
    "WeatherStart": "Clear",
    "WeatherEnd": "Clear"
  },
  {
    "TimestampMs": 1776713832794,
    "SessionId": "b21333f1-04ad-47d9-82d5-3b45f191f730",
    "Track": "spa",
    "Layout": "",
    "Car": "bmw_z4_gt3",
    "LapTimeMs": 151467,
    "WeatherCategory": "Clear",
    "WeatherStart": "Clear",
    "WeatherEnd": "Clear"
  },
  {
    "TimestampMs": 1776713994899,
    "SessionId": "b21333f1-04ad-47d9-82d5-3b45f191f730",
    "Track": "spa",
    "Layout": "",
    "Car": "bmw_z4_gt3",
    "LapTimeMs": 162103,
    "WeatherCategory": "Clear",
    "WeatherStart": "Clear",
    "WeatherEnd": "Clear"
  },
  {
    "TimestampMs": 1776714145003,
    "SessionId": "b21333f1-04ad-47d9-82d5-3b45f191f730",
    "Track": "spa",
    "Layout": "",
    "Car": "bmw_z4_gt3",
    "LapTimeMs": 150108,
    "WeatherCategory": "Clear",
    "WeatherStart": "Clear",
    "WeatherEnd": "Clear"
  },
  {
    "TimestampMs": 1776714301051,
    "SessionId": "b21333f1-04ad-47d9-82d5-3b45f191f730",
    "Track": "spa",
    "Layout": "",
    "Car": "bmw_z4_gt3",
    "LapTimeMs": 156046,
    "WeatherCategory": "Clear",
    "WeatherStart": "Clear",
    "WeatherEnd": "Clear"
  }
]