[
  {
    "TimestampMs" : 1774662922894,
    "SessionId" : "6a2f0db3-1cd5-436a-97cc-bf08272c5f09",
    "Track" : "ks_silverstone",
    "WeatherCategory" : "Clear",
    "WeatherStart" : "Clear",
    "Layout" : "gp",
    "LapTimeMs" : 129905,
    "WeatherEnd" : "Clear",
    "Car" : "bmw_m3_gt2"
  },
  {
    "Car" : "bmw_m3_gt2",
    "WeatherCategory" : "Clear",
    "Track" : "ks_silverstone",
    "SessionId" : "6a2f0db3-1cd5-436a-97cc-bf08272c5f09",
    "TimestampMs" : 1774663049611,
    "Layout" : "gp",
    "LapTimeMs" : 126718,
    "WeatherStart" : "Clear",
    "WeatherEnd" : "Clear"
  },
  {
    "SessionId" : "6a2f0db3-1cd5-436a-97cc-bf08272c5f09",
    "TimestampMs" : 1774663178200,
    "Track" : "ks_silverstone",
    "WeatherCategory" : "Clear",
    "WeatherEnd" : "Clear",
    "WeatherStart" : "Clear",
    "Layout" : "gp",
    "LapTimeMs" : 128589,
    "Car" : "bmw_m3_gt2"
  }
]
