[
  {
    "TimestampMs": 1775762973093,
    "SessionId": "3bb86df9-8d60-4ded-8aa9-10950cd72644",
    "Track": "spa",
    "Layout": "",
    "Car": "ferrari_458_gt2",
    "LapTimeMs": 152264,
    "WeatherCategory": "Clear",
    "WeatherStart": "Clear",
    "WeatherEnd": "Clear"
  },
  {
    "TimestampMs": 1775763548428,
    "SessionId": "3bb86df9-8d60-4ded-8aa9-10950cd72644",
    "Track": "spa",
    "Layout": "",
    "Car": "ferrari_458_gt2",
    "LapTimeMs": 155356,
    "WeatherCategory": "Clear",
    "WeatherStart": "Clear",
    "WeatherEnd": "Clear"
  },
  {
    "TimestampMs": 1775763711033,
    "SessionId": "3bb86df9-8d60-4ded-8aa9-10950cd72644",
    "Track": "spa",
    "Layout": "",
    "Car": "ferrari_458_gt2",
    "LapTimeMs": 162609,
    "WeatherCategory": "Clear",
    "WeatherStart": "Clear",
    "WeatherEnd": "Clear"
  },
  {
    "TimestampMs": 1775763878627,
    "SessionId": "3bb86df9-8d60-4ded-8aa9-10950cd72644",
    "Track": "spa",
    "Layout": "",
    "Car": "ferrari_458_gt2",
    "LapTimeMs": 167598,
    "WeatherCategory": "Clear",
    "WeatherStart": "Clear",
    "WeatherEnd": "Clear"
  },
  {
    "TimestampMs": 1775764025700,
    "SessionId": "3bb86df9-8d60-4ded-8aa9-10950cd72644",
    "Track": "spa",
    "Layout": "",
    "Car": "ferrari_458_gt2",
    "LapTimeMs": 147055,
    "WeatherCategory": "Clear",
    "WeatherStart": "Clear",
    "WeatherEnd": "Clear"
  },
  {
    "TimestampMs": 1775764177259,
    "SessionId": "3bb86df9-8d60-4ded-8aa9-10950cd72644",
    "Track": "spa",
    "Layout": "",
    "Car": "ferrari_458_gt2",
    "LapTimeMs": 151579,
    "WeatherCategory": "Clear",
    "WeatherStart": "Clear",
    "WeatherEnd": "Clear"
  },
  {
    "TimestampMs": 1775764692328,
    "SessionId": "3bb86df9-8d60-4ded-8aa9-10950cd72644",
    "Track": "spa",
    "Layout": "",
    "Car": "ferrari_458_gt2",
    "LapTimeMs": 146649,
    "WeatherCategory": "Clear",
    "WeatherStart": "Clear",
    "WeatherEnd": "Clear"
  },
  {
    "TimestampMs": 1775764864184,
    "SessionId": "3bb86df9-8d60-4ded-8aa9-10950cd72644",
    "Track": "spa",
    "Layout": "",
    "Car": "ferrari_458_gt2",
    "LapTimeMs": 171855,
    "WeatherCategory": "Clear",
    "WeatherStart": "Clear",
    "WeatherEnd": "Clear"
  },
  {
    "TimestampMs": 1775765026762,
    "SessionId": "3bb86df9-8d60-4ded-8aa9-10950cd72644",
    "Track": "spa",
    "Layout": "",
    "Car": "ferrari_458_gt2",
    "LapTimeMs": 162584,
    "WeatherCategory": "Clear",
    "WeatherStart": "Clear",
    "WeatherEnd": "Clear"
  },
  {
    "TimestampMs": 1775765179052,
    "SessionId": "3bb86df9-8d60-4ded-8aa9-10950cd72644",
    "Track": "spa",
    "Layout": "",
    "Car": "ferrari_458_gt2",
    "LapTimeMs": 152292,
    "WeatherCategory": "Clear",
    "WeatherStart": "Clear",
    "WeatherEnd": "Clear"
  },
  {
    "TimestampMs": 1775765334475,
    "SessionId": "3bb86df9-8d60-4ded-8aa9-10950cd72644",
    "Track": "spa",
    "Layout": "",
    "Car": "ferrari_458_gt2",
    "LapTimeMs": 155425,
    "WeatherCategory": "Clear",
    "WeatherStart": "Clear",
    "WeatherEnd": "Clear"
  }
]