[{"Car":"ferrari_458_gt2","Track":"ks_silverstone","WeatherEnd":"Clear","WeatherCategory":"Clear","SessionId":"48a47624-87f0-4884-9099-d5b3182f650e","TimestampMs":1775165930393,"WeatherStart":"Clear","LapTimeMs":127852,"Layout":"gp"},{"LapTimeMs":127741,"TimestampMs":1775166566717,"WeatherStart":"Clear","Layout":"gp","Car":"bmw_z4_gt3","Track":"ks_silverstone","WeatherCategory":"Clear","SessionId":"48a47624-87f0-4884-9099-d5b3182f650e","WeatherEnd":"Clear"},{"WeatherStart":"Clear","TimestampMs":1775166693577,"LapTimeMs":126860,"Layout":"gp","Track":"ks_silverstone","Car":"bmw_z4_gt3","WeatherEnd":"Clear","WeatherCategory":"Clear","SessionId":"48a47624-87f0-4884-9099-d5b3182f650e"},{"LapTimeMs":126367,"WeatherStart":"Clear","TimestampMs":1775166819959,"Layout":"gp","Track":"ks_silverstone","Car":"bmw_z4_gt3","SessionId":"48a47624-87f0-4884-9099-d5b3182f650e","WeatherCategory":"Clear","WeatherEnd":"Clear"},{"Track":"ks_silverstone","Car":"bmw_z4_gt3","WeatherCategory":"Clear","SessionId":"48a47624-87f0-4884-9099-d5b3182f650e","WeatherEnd":"Clear","LapTimeMs":126699,"WeatherStart":"Clear","TimestampMs":1775166946650,"Layout":"gp"},{"Layout":"gp","WeatherStart":"Clear","TimestampMs":1775167202146,"LapTimeMs":127564,"WeatherEnd":"Clear","SessionId":"48a47624-87f0-4884-9099-d5b3182f650e","WeatherCategory":"Clear","Track":"ks_silverstone","Car":"bmw_z4_gt3"},{"Track":"ks_silverstone","Car":"bmw_z4_gt3","WeatherCategory":"Clear","SessionId":"48a47624-87f0-4884-9099-d5b3182f650e","WeatherEnd":"Clear","LapTimeMs":126699,"WeatherStart":"Clear","TimestampMs":1775167328845,"Layout":"gp"},{"WeatherEnd":"Clear","WeatherCategory":"Clear","SessionId":"48a47624-87f0-4884-9099-d5b3182f650e","Track":"ks_silverstone","Car":"bmw_z4_gt3","Layout":"gp","WeatherStart":"Clear","TimestampMs":1775167589492,"LapTimeMs":125924},{"Layout":"gp","LapTimeMs":126350,"TimestampMs":1775167887390,"WeatherStart":"Clear","WeatherCategory":"Clear","SessionId":"48a47624-87f0-4884-9099-d5b3182f650e","WeatherEnd":"Clear","Car":"bmw_z4_gt3","Track":"ks_silverstone"},{"Layout":"gp","TimestampMs":1775168013691,"WeatherStart":"Clear","LapTimeMs":126300,"WeatherEnd":"Clear","SessionId":"48a47624-87f0-4884-9099-d5b3182f650e","WeatherCategory":"Clear","Car":"bmw_z4_gt3","Track":"ks_silverstone"},{"Layout":"gp","TimestampMs":1775168141087,"WeatherStart":"Clear","LapTimeMs":127395,"WeatherEnd":"Clear","SessionId":"48a47624-87f0-4884-9099-d5b3182f650e","WeatherCategory":"Clear","Car":"bmw_z4_gt3","Track":"ks_silverstone"},{"WeatherStart":"Clear","TimestampMs":1775168394320,"LapTimeMs":127157,"Layout":"gp","Track":"ks_silverstone","Car":"bmw_z4_gt3","WeatherEnd":"Clear","SessionId":"48a47624-87f0-4884-9099-d5b3182f650e","WeatherCategory":"Clear"},{"Layout":"gp","LapTimeMs":126677,"TimestampMs":1775168521002,"WeatherStart":"Clear","WeatherCategory":"Clear","SessionId":"48a47624-87f0-4884-9099-d5b3182f650e","WeatherEnd":"Clear","Car":"bmw_z4_gt3","Track":"ks_silverstone"}]