[{"WeatherEnd":"Cold","WeatherCategory":"Mixed","SessionId":"bf8fa79d-335d-47de-bd65-ac0a4eaffb64","Car":"bmw_z4_gt3","Track":"spa","Layout":"","TimestampMs":1774309693433,"WeatherStart":"Mist","LapTimeMs":157033},{"Car":"bmw_z4_gt3","Track":"spa","SessionId":"bf8fa79d-335d-47de-bd65-ac0a4eaffb64","WeatherCategory":"Mixed","WeatherEnd":"Transition","LapTimeMs":180714,"TimestampMs":1774310275209,"WeatherStart":"Cold","Layout":""},{"WeatherCategory":"Mixed","SessionId":"bf8fa79d-335d-47de-bd65-ac0a4eaffb64","WeatherEnd":"Drizzle","Car":"bmw_z4_gt3","Track":"spa","Layout":"","LapTimeMs":180602,"TimestampMs":1774310455814,"WeatherStart":"Transition"},{"Layout":"","LapTimeMs":167331,"WeatherStart":"Drizzle","TimestampMs":1774310623142,"SessionId":"bf8fa79d-335d-47de-bd65-ac0a4eaffb64","WeatherCategory":"Drizzle","WeatherEnd":"Drizzle","Track":"spa","Car":"bmw_z4_gt3"},{"WeatherStart":"Drizzle","TimestampMs":1774310792870,"LapTimeMs":169730,"Layout":"","Track":"spa","Car":"bmw_z4_gt3","WeatherEnd":"Drizzle","WeatherCategory":"Drizzle","SessionId":"bf8fa79d-335d-47de-bd65-ac0a4eaffb64"},{"Car":"bmw_z4_gt3","Track":"spa","WeatherEnd":"ScatteredClouds","SessionId":"2314ed80-3df3-4e31-b015-95059e9b039d","WeatherCategory":"Mixed","TimestampMs":1774567443200,"WeatherStart":"Cold","LapTimeMs":159783,"Layout":""},{"Layout":"","LapTimeMs":149435,"TimestampMs":1774567592598,"WeatherStart":"ScatteredClouds","WeatherCategory":"ScatteredClouds","SessionId":"2314ed80-3df3-4e31-b015-95059e9b039d","WeatherEnd":"ScatteredClouds","Car":"bmw_z4_gt3","Track":"spa"},{"SessionId":"2314ed80-3df3-4e31-b015-95059e9b039d","WeatherCategory":"ScatteredClouds","WeatherEnd":"ScatteredClouds","Track":"spa","Car":"bmw_z4_gt3","Layout":"","LapTimeMs":169338,"WeatherStart":"ScatteredClouds","TimestampMs":1774567761935},{"TimestampMs":1774567909131,"WeatherStart":"ScatteredClouds","LapTimeMs":147195,"Layout":"","Car":"bmw_z4_gt3","Track":"spa","WeatherEnd":"ScatteredClouds","WeatherCategory":"ScatteredClouds","SessionId":"2314ed80-3df3-4e31-b015-95059e9b039d"},{"WeatherStart":"ScatteredClouds","TimestampMs":1774568065315,"LapTimeMs":156185,"Layout":"","Track":"spa","Car":"bmw_z4_gt3","WeatherEnd":"Clear","WeatherCategory":"Mixed","SessionId":"2314ed80-3df3-4e31-b015-95059e9b039d"},{"Car":"bmw_z4_gt3","Track":"spa","WeatherEnd":"Transition","SessionId":"2314ed80-3df3-4e31-b015-95059e9b039d","WeatherCategory":"Mixed","TimestampMs":1774569880868,"WeatherStart":"Clear","LapTimeMs":162881,"Layout":""},{"SessionId":"0dd89ff5-1a1c-4296-8e8c-a90ed6a0d15a","WeatherCategory":"Clear","WeatherEnd":"Clear","Track":"spa","Car":"bmw_z4_gt3","Layout":"","LapTimeMs":151108,"WeatherStart":"Clear","TimestampMs":1774751197242},{"LapTimeMs":152465,"TimestampMs":1774751349707,"WeatherStart":"Clear","Layout":"","Car":"bmw_z4_gt3","Track":"spa","WeatherCategory":"Clear","SessionId":"0dd89ff5-1a1c-4296-8e8c-a90ed6a0d15a","WeatherEnd":"Clear"},{"SessionId":"0dd89ff5-1a1c-4296-8e8c-a90ed6a0d15a","WeatherCategory":"Clear","WeatherEnd":"Clear","Car":"bmw_z4_gt3","Track":"spa","Layout":"","LapTimeMs":156098,"TimestampMs":1774751505805,"WeatherStart":"Clear"},{"WeatherEnd":"Clear","SessionId":"0dd89ff5-1a1c-4296-8e8c-a90ed6a0d15a","WeatherCategory":"Clear","Car":"bmw_z4_gt3","Track":"spa","Layout":"","TimestampMs":1774751655039,"WeatherStart":"Clear","LapTimeMs":149236},{"SessionId":"0dd89ff5-1a1c-4296-8e8c-a90ed6a0d15a","WeatherCategory":"Clear","WeatherEnd":"Clear","Track":"spa","Car":"bmw_z4_gt3","Layout":"","LapTimeMs":151651,"WeatherStart":"Clear","TimestampMs":1774751806690}]