[
  {
    "TimestampMs": 1775966521729,
    "SessionId": "ee76ed90-a65d-47ab-acc2-26f83a461bb6",
    "Track": "spa",
    "Layout": "",
    "Car": "mclaren_mp412c_gt3",
    "LapTimeMs": 150344,
    "WeatherCategory": "Clear",
    "WeatherStart": "Clear",
    "WeatherEnd": "Clear"
  },
  {
    "TimestampMs": 1775966682648,
    "SessionId": "ee76ed90-a65d-47ab-acc2-26f83a461bb6",
    "Track": "spa",
    "Layout": "",
    "Car": "mclaren_mp412c_gt3",
    "LapTimeMs": 160923,
    "WeatherCategory": "Clear",
    "WeatherStart": "Clear",
    "WeatherEnd": "Clear"
  },
  {
    "TimestampMs": 1775966840904,
    "SessionId": "ee76ed90-a65d-47ab-acc2-26f83a461bb6",
    "Track": "spa",
    "Layout": "",
    "Car": "mclaren_mp412c_gt3",
    "LapTimeMs": 158260,
    "WeatherCategory": "Clear",
    "WeatherStart": "Clear",
    "WeatherEnd": "Clear"
  },
  {
    "TimestampMs": 1775966989704,
    "SessionId": "ee76ed90-a65d-47ab-acc2-26f83a461bb6",
    "Track": "spa",
    "Layout": "",
    "Car": "mclaren_mp412c_gt3",
    "LapTimeMs": 148803,
    "WeatherCategory": "Clear",
    "WeatherStart": "Clear",
    "WeatherEnd": "Clear"
  },
  {
    "TimestampMs": 1775967138056,
    "SessionId": "ee76ed90-a65d-47ab-acc2-26f83a461bb6",
    "Track": "spa",
    "Layout": "",
    "Car": "mclaren_mp412c_gt3",
    "LapTimeMs": 148355,
    "WeatherCategory": "Clear",
    "WeatherStart": "Clear",
    "WeatherEnd": "Clear"
  }
]